conflux/__init__.py
conflux/base.py
conflux/exceptions.py
conflux/handlers.py
conflux/types.py
conflux/utils.py
conflux/mcp/client.py
conflux/retrieval/__init__.py
conflux/retrieval/faiss.py
conflux/retrieval/join_policies.py
conflux_ai-0.7.2.dist-info/METADATA
conflux_ai-0.7.2.dist-info/WHEEL
conflux_ai-0.7.2.dist-info/licenses/LICENSE
conflux_ai-0.7.2.dist-info/RECORD
